pedinf/__init__.py
pedinf/diagnostics.py
pedinf/posterior.py
pedinf/spline.py
pedinf/analysis/__init__.py
pedinf/analysis/inversions.py
pedinf/analysis/pressure.py
pedinf/analysis/profile.py
pedinf/analysis/separatrix.py
pedinf/analysis/utils.py
pedinf/models/__init__.py
pedinf/models/base.py
pedinf/models/exspline.py
pedinf/models/logispline.py
pedinf/models/lpm.py
pedinf/models/mtanh.py
pedinf/models/utils.py
pedinf/spectrum/__init__.py
pedinf/spectrum/jax.py
pedinf/spectrum/numba.py
pedinf/spectrum/numpy.py
pedestal_inference-0.5.0.dist-info/LICENSE
pedestal_inference-0.5.0.dist-info/METADATA
pedestal_inference-0.5.0.dist-info/WHEEL
pedestal_inference-0.5.0.dist-info/top_level.txt
pedestal_inference-0.5.0.dist-info/RECORD
