Metadata-Version: 2.2
Name: pedestal-inference
Version: 0.5.0
Summary: A collection of Python tools for plasma-edge Thomson-scattering analysis
Author-email: Chris Bowman <chris.bowman.physics@gmail.com>
License: MIT License
Project-URL: homepage, https://github.com/C-bowman/pedestal-inference
Project-URL: documentation, https://pedestal-inference.readthedocs.io/
Classifier: Programming Language :: Python :: 3
Classifier: License :: OSI Approved :: MIT License
Classifier: Operating System :: OS Independent
Requires-Python: >=3.9
License-File: LICENSE
Requires-Dist: numpy>=1.22.4
Requires-Dist: scipy>=1.10.1
Requires-Dist: inference-tools>=0.14.0
Provides-Extra: tests
Requires-Dist: pytest>=3.3.0; extra == "tests"
Requires-Dist: pytest-cov>=3.0.0; extra == "tests"
Provides-Extra: jit
Requires-Dist: jax>=0.4.30; extra == "jit"
Requires-Dist: numba>=0.61.0; extra == "jit"
